tokenmint/__init__.py
tokenmint/py.typed
tokenmint/cache/__init__.py
tokenmint/cache/_replay_cache.py
tokenmint/exceptions/__init__.py
tokenmint/exceptions/_token_configuration_error.py
tokenmint/schema/__init__.py
tokenmint/schema/_claim_dict.py
tokenmint/services/__init__.py
tokenmint/services/_token_key_pair.py
tokenmint/services/_token_mint.py
tokenmint/settings/__init__.py
tokenmint/settings/_settings.py
tokenmint/stores/__init__.py
tokenmint/stores/_key_store.py
tokenmint-0.1.2.dist-info/METADATA
tokenmint-0.1.2.dist-info/WHEEL
tokenmint-0.1.2.dist-info/entry_points.txt
tokenmint-0.1.2.dist-info/licenses/LICENSE
tokenmint-0.1.2.dist-info/RECORD
