Metadata-Version: 2.4
Name: tokenmint
Version: 0.1.2
Summary: A modern Python library for issuing and verifying limited-time, scoped, and replay-protected tokens.
Project-URL: Homepage, https://github.com/shaileshpandit141/tokenmint
Project-URL: Documentation, https://shaileshpandit141.github.io/tokenmint
Project-URL: Source, https://github.com/shaileshpandit141/tokenmint
Project-URL: Issues, https://github.com/shaileshpandit141/tokenmint/issues
Project-URL: License, https://github.com/shaileshpandit141/tokenmint/blob/main/LICENSE
Author-email: shaileshpandit141 <shaileshpandit141@gmail.com>
License: # MIT License
License-File: LICENSE
Keywords: Ed25519,EdDSA,Redis,api-security,auth,authentication,authorization,cryptography,email-verification,ephemeral-tokens,jwt,key-rotation,magic-link,password-reset,replay-protection,scoped-tokens,secure-tokens,session,time-limited-tokens,token-auth,tokens
Classifier: Development Status :: 4 - Beta
Classifier: Intended Audience :: Developers
Classifier: License :: OSI Approved :: MIT License
Classifier: Programming Language :: Python
Classifier: Programming Language :: Python :: 3.10
Classifier: Programming Language :: Python :: 3.11
Classifier: Programming Language :: Python :: 3.12
Classifier: Programming Language :: Python :: 3.13
Classifier: Topic :: Security
Classifier: Topic :: Security :: Cryptography
Classifier: Topic :: Software Development :: Libraries
Classifier: Topic :: Software Development :: Libraries :: Python Modules
Classifier: Typing :: Typed
Requires-Python: >=3.13
Requires-Dist: cryptography>=45.0.6
Requires-Dist: pyjwt>=2.10.1
Requires-Dist: redis>=6.4.0
Provides-Extra: dev
Requires-Dist: mypy; extra == 'dev'
Requires-Dist: ruff; extra == 'dev'
